goldilock/__init__.py
goldilock/common.py
goldilock/goldilock.py
goldilock-0.0.2.dist-info/LICENSE
goldilock-0.0.2.dist-info/METADATA
goldilock-0.0.2.dist-info/WHEEL
goldilock-0.0.2.dist-info/top_level.txt
goldilock-0.0.2.dist-info/RECORD
