Metadata-Version: 2.1
Name: goldilock
Version: 0.0.2
Summary: A basic python package
Home-page: https://github.com/NandhiniKRC/goldilock
Author: Nandhini Ramachandran
Author-email: nandhini.krc@gmail.com
License: MIT license
Keywords: goldilock
Classifier: Intended Audience :: Developers
Classifier: License :: OSI Approved :: MIT License
Classifier: Natural Language :: English
Classifier: Programming Language :: Python :: 3
Classifier: Programming Language :: Python :: 3.8
Classifier: Programming Language :: Python :: 3.9
Classifier: Programming Language :: Python :: 3.10
Classifier: Programming Language :: Python :: 3.11
Requires-Python: >=3.8
License-File: LICENSE
